plugins/__init__.py
plugins/plug_64094.py
plugins/plug_94251.py
radio/__init__.py
radio/app.py
radio/config.py
radio/core/__init__.py
radio/core/classes.py
radio/core/log.py
radio/core/player.py
radio/core/recorder.py
radio/core/utils.py
radio/handlers/__init__.py
radio/handlers/exchange.py
radio/tui/__init__.py
radio/tui/buffers.py
radio/tui/commands.py
radio/tui/styles.py
radioz-0.0.dev5.dist-info/LICENSE
radioz-0.0.dev5.dist-info/METADATA
radioz-0.0.dev5.dist-info/WHEEL
radioz-0.0.dev5.dist-info/entry_points.txt
radioz-0.0.dev5.dist-info/top_level.txt
radioz-0.0.dev5.dist-info/RECORD
